README.rst
setup.cfg
setup.py
hackasmlexer/__init__.py
hackasmlexer/hacklexer.py
pygments_hackasm_lexer.egg-info/PKG-INFO
pygments_hackasm_lexer.egg-info/SOURCES.txt
pygments_hackasm_lexer.egg-info/dependency_links.txt
pygments_hackasm_lexer.egg-info/entry_points.txt
pygments_hackasm_lexer.egg-info/requires.txt
pygments_hackasm_lexer.egg-info/top_level.txt